lerobothackathonenv/__init__.py
lerobothackathonenv/env.py
lerobothackathonenv/lerobot_types.py
lerobothackathonenv/models/meshes/LeRobot-SO101/base_motor_holder_so101_v1.part
lerobothackathonenv/models/meshes/LeRobot-SO101/base_motor_holder_so101_v1.stl
lerobothackathonenv/models/meshes/LeRobot-SO101/base_so101_v2.part
lerobothackathonenv/models/meshes/LeRobot-SO101/base_so101_v2.stl
lerobothackathonenv/models/meshes/LeRobot-SO101/motor_holder_so101_base_v1.part
lerobothackathonenv/models/meshes/LeRobot-SO101/motor_holder_so101_base_v1.stl
lerobothackathonenv/models/meshes/LeRobot-SO101/motor_holder_so101_wrist_v1.part
lerobothackathonenv/models/meshes/LeRobot-SO101/motor_holder_so101_wrist_v1.stl
lerobothackathonenv/models/meshes/LeRobot-SO101/moving_jaw_so101_v1.part
lerobothackathonenv/models/meshes/LeRobot-SO101/moving_jaw_so101_v1.stl
lerobothackathonenv/models/meshes/LeRobot-SO101/rotation_pitch_so101_v1.part
lerobothackathonenv/models/meshes/LeRobot-SO101/rotation_pitch_so101_v1.stl
lerobothackathonenv/models/meshes/LeRobot-SO101/sts3215_03a_no_horn_v1.part
lerobothackathonenv/models/meshes/LeRobot-SO101/sts3215_03a_no_horn_v1.stl
lerobothackathonenv/models/meshes/LeRobot-SO101/sts3215_03a_v1.part
lerobothackathonenv/models/meshes/LeRobot-SO101/sts3215_03a_v1.stl
lerobothackathonenv/models/meshes/LeRobot-SO101/under_arm_so101_v1.part
lerobothackathonenv/models/meshes/LeRobot-SO101/under_arm_so101_v1.stl
lerobothackathonenv/models/meshes/LeRobot-SO101/upper_arm_so101_v1.part
lerobothackathonenv/models/meshes/LeRobot-SO101/upper_arm_so101_v1.stl
lerobothackathonenv/models/meshes/LeRobot-SO101/waveshare_mounting_plate_so101_v2.part
lerobothackathonenv/models/meshes/LeRobot-SO101/waveshare_mounting_plate_so101_v2.stl
lerobothackathonenv/models/meshes/LeRobot-SO101/wrist_roll_follower_so101_v1.part
lerobothackathonenv/models/meshes/LeRobot-SO101/wrist_roll_follower_so101_v1.stl
lerobothackathonenv/models/meshes/LeRobot-SO101/wrist_roll_pitch_so101_v2.part
lerobothackathonenv-0.2.0.dist-info/WHEEL
lerobothackathonenv-0.2.0.dist-info/METADATA
lerobothackathonenv-0.2.0.dist-info/RECORD
