Metadata-Version: 2.3
Name: lerobothackathonenv
Version: 0.2.0
Summary: Add your description here
Requires-Dist: dm-control>=1.0.34
Requires-Dist: gymnasium>=1.2.2
Requires-Dist: mujoco>=3.3.7
Requires-Python: >=3.10, <3.13
